{"id":20726,"crosswords":{"no":"020726","difficulty":3,"created":"2025-09-16","start":"2025-10-10","partner":"spiegel.de","cols":9,"rows":9,"clues":[{"id":1,"col":0,"row":0,"s":[0,1],"e":[4,1],"t":"Landkar-\ntenwerk"},{"id":2,"col":0,"row":2,"s":[1,2],"e":[6,2],"t":"nachträg-\nliche\nInstal-\nlation"},{"id":3,"col":0,"row":3,"s":[1,3],"e":[3,3],"t":"Höhen-\nzug bei\nBraun-\nschweig"},{"id":4,"col":0,"row":4,"s":[1,4],"e":[2,4],"t":"spanisch:\nja"},{"id":5,"col":0,"row":6,"s":[0,5],"e":[2,5],"t":"griech.\nUnheils-\ngöttin"},{"id":6,"col":0,"row":8,"s":[0,7],"e":[4,7],"t":"das Einho-\nlen bereit-\ngestellter\nInfos"},{"id":7,"col":1,"row":0,"s":[1,1],"e":[1,8],"t":"Gaststätte\nohne\nAlkohol-\nausschank"},{"id":8,"col":2,"row":0,"s":[2,1],"e":[2,5],"t":"Zwiebel-\npflanze,\nZier-\npflanze"},{"id":9,"col":2,"row":6,"s":[3,6],"e":[8,6],"t":"Höhe-\npunkt\neiner Auf-\nführung"},{"id":10,"col":2,"row":8,"s":[3,8],"e":[8,8],"t":"ziegen-\nähnliches\nGebirgs-\ntier"},{"id":11,"col":3,"row":0,"s":[3,1],"e":[3,3],"t":"Abk.:\nAnmer-\nkung"},{"id":12,"col":3,"row":4,"s":[4,4],"e":[7,4],"t":"säuerlich,\nleicht\nbitter"},{"id":13,"col":3,"row":5,"s":[3,6],"e":[3,8],"t":"mit ...\nund\nRecht"},{"id":14,"col":4,"row":3,"s":[4,4],"e":[4,8],"t":"Küsten-\nstadt im\nNorden\nIsreals"},{"id":15,"col":5,"row":0,"s":[4,0],"e":[4,2],"t":"Anschluss\nbeim PC\n(Abk.)"},{"id":16,"col":5,"row":1,"s":[6,1],"e":[8,1],"t":"Univer-\nsum,\nWeltraum"},{"id":17,"col":5,"row":3,"s":[6,3],"e":[8,3],"t":"griech.\nGöttin\nder Mor-\ngenröte"},{"id":18,"col":5,"row":5,"s":[6,5],"e":[8,5],"t":"grausam,\ngefühllos"},{"id":19,"col":5,"row":7,"s":[6,7],"e":[8,7],"t":"Teil des\nPferde-\nfußes"},{"id":20,"col":7,"row":0,"s":[6,0],"e":[6,8],"t":"Art von\nSahne"},{"id":21,"col":7,"row":2,"s":[7,3],"e":[7,8],"t":"kleine\nGeld-\nspende"},{"id":22,"col":8,"row":0,"s":[8,1],"e":[8,3],"t":"Ruf zum\nStarten\neines\nRennens"},{"id":23,"col":8,"row":4,"s":[8,5],"e":[8,8],"t":"Gärstoff"}],"solutions":[{"id":1,"col":4,"row":2},{"id":2,"col":4,"row":6},{"id":3,"col":7,"row":3},{"id":4,"col":3,"row":3},{"id":5,"col":0,"row":7},{"id":6,"col":1,"row":4},{"id":7,"col":6,"row":0},{"id":8,"col":2,"row":5}],"solved":[["","","","","U","","S","",""],["A","T","L","A","S","","A","L","L"],["","E","I","N","B","A","U","","O"],["","E","L","M","","","E","O","S"],["","S","I","","H","E","R","B",""],["A","T","E","","A","","R","O","H"],["","U","","F","I","N","A","L","E"],["A","B","R","U","F","","H","U","F"],["","E","","G","A","E","M","S","E"]],"letters":[],"import_file_date":"2025-09-15","import_file_time":"06:02:10:3","import_file_name":"fcs/spiegel/2025-08-26/9x9/crossword_13336_raetsel4u_kr3m_spiegel_9x9_d4_DE.fcs","converted_file_date":"2025-09-16","converted_file_time":"08:32:39:4","licensed_for":"spiegel.de","words":23,"solution_word":"BIOMASSE","empty_fields":0,"double_challenges":0,"converter_version":"0.0.11","supplier":"raetsel4u"}}