{"id":19703,"crosswords":{"no":"019703","difficulty":3,"created":"2025-05-19","start":"2025-07-09","partner":"spiegel.de","cols":9,"rows":9,"clues":[{"id":1,"col":0,"row":0,"s":[0,1],"e":[3,1],"t":"Beklei-\ndungs-\nstück"},{"id":2,"col":0,"row":2,"s":[1,2],"e":[6,2],"t":"ital.\nHafen-\nstadt am\nVesuv"},{"id":3,"col":0,"row":3,"s":[0,4],"e":[3,4],"t":"Stech-\ngerät des\nLeder-\narbeiters"},{"id":4,"col":0,"row":5,"s":[1,5],"e":[2,5],"t":"Doppel-\nvokal"},{"id":5,"col":0,"row":6,"s":[1,6],"e":[8,6],"t":"Neben-\nfluss des\nMissis-\nsippi"},{"id":6,"col":0,"row":8,"s":[0,7],"e":[4,7],"t":"brauner\nFarbton"},{"id":7,"col":1,"row":0,"s":[1,1],"e":[1,8],"t":"heftig,\nungestüm"},{"id":8,"col":2,"row":0,"s":[2,1],"e":[2,2],"t":"Abk.:\nMengen-\neinheit"},{"id":9,"col":2,"row":3,"s":[2,4],"e":[2,7],"t":"Körper\neines\nLebe-\nwesens"},{"id":10,"col":2,"row":8,"s":[3,8],"e":[8,8],"t":"Haft-\npflich-\ntiger,\nGarant"},{"id":11,"col":3,"row":0,"s":[3,1],"e":[3,4],"t":"Spiel-\nkarte im\nfrz. Blatt"},{"id":12,"col":3,"row":5,"s":[3,6],"e":[3,8],"t":"olymp.\nKürzel:\nSerbien"},{"id":13,"col":4,"row":0,"s":[5,0],"e":[5,4],"t":"Tresen,\nSchank-\ntisch"},{"id":14,"col":4,"row":1,"s":[5,1],"e":[8,1],"t":"Vieh-\nhüter"},{"id":15,"col":4,"row":3,"s":[5,3],"e":[8,3],"t":"Blatt-\ngemüse"},{"id":16,"col":4,"row":4,"s":[4,5],"e":[4,8],"t":"Sohn\nIsaaks\nim A. T."},{"id":17,"col":5,"row":5,"s":[6,5],"e":[8,5],"t":"Vergehen"},{"id":18,"col":5,"row":7,"s":[6,7],"e":[8,7],"t":"feier-\nliches\nVerspre-\nchen"},{"id":19,"col":6,"row":4,"s":[6,5],"e":[6,8],"t":"Haus-\neingang"},{"id":20,"col":7,"row":0,"s":[6,0],"e":[6,3],"t":"Gär-\nfutter-\nbehälter"},{"id":21,"col":7,"row":2,"s":[7,3],"e":[7,8],"t":"vertrackt,\nkompli-\nziert,\nheikel"},{"id":22,"col":8,"row":0,"s":[8,1],"e":[8,3],"t":"Gelände-\nform"},{"id":23,"col":8,"row":4,"s":[8,5],"e":[8,8],"t":"Ebbe und\nFlut\n(norddt.)"}],"solutions":[{"id":1,"col":0,"row":4},{"id":2,"col":4,"row":8},{"id":3,"col":8,"row":1},{"id":4,"col":7,"row":4},{"id":5,"col":3,"row":7},{"id":6,"col":5,"row":3},{"id":7,"col":2,"row":6},{"id":8,"col":6,"row":7}],"solved":[["","","","","","T","S","",""],["H","E","M","D","","H","I","R","T"],["","N","E","A","P","E","L","","A"],["","T","","M","","K","O","H","L"],["A","H","L","E","","E","","A",""],["","E","E","","E","","T","A","T"],["","M","I","S","S","O","U","R","I"],["U","M","B","R","A","","E","I","D"],["","T","","B","U","E","R","G","E"]],"letters":[],"import_file_date":"2025-05-12","import_file_time":"22:04:25:0","import_file_name":"fcs/spiegel/2025-05-14/12461_12491_spiegel_9x9_d4_DE/crossword_12468_raetsel4u_kr3m_spiegel_9x9_d4_DE.fcs","converted_file_date":"2025-05-19","converted_file_time":"05:06:14:1","licensed_for":"spiegel.de","words":23,"solution_word":"AUTARKIE","empty_fields":0,"double_challenges":0,"converter_version":"0.0.11","supplier":"raetsel4u"}}